pipeless_ai_plugins/kafka/README.md
pipeless_ai_plugins/kafka/__init__.py
pipeless_ai_plugins/kafka/kafka.py
pipeless_ai_plugins/kafka/metadata.py
pipeless_ai_plugins-0.1.1.dist-info/LICENSE
pipeless_ai_plugins-0.1.1.dist-info/METADATA
pipeless_ai_plugins-0.1.1.dist-info/WHEEL
pipeless_ai_plugins-0.1.1.dist-info/RECORD
